{
  "chief": {
    "title": "Начальник Центра",
    "staffId": 1
  },
  "vise_chief": {
    "title": "Заместитель начальника Центра",
    "staffId": 2
  },
  "vise_chief_engineer": {
    "title": "Заместитель начальника Центра - главный инженер",
    "staffId": 3
  },
  "vise_chief_iar": {
    "title": "Заместитель начальника Центра по ИАР",
    "staffId": 4
  },
  "assistant_chief": {
    "title": "Помощник Начальника Центра по работе с личным составом",
    "staffId": 5
  },
  "mobster": {
    "title": "Старший офицер по моб.подготовке",
    "staffId": 88
  },
  "duty_assistant": {
    "title": "Помощник дежурного",
    "type": "rotating",
    "staffIds": [15, 16, 17]
  }
}
